seolTest/test1.py
seolTest/test2.py
seolTest-0.0.0.2.dist-info/METADATA
seolTest-0.0.0.2.dist-info/WHEEL
seolTest-0.0.0.2.dist-info/top_level.txt
seolTest-0.0.0.2.dist-info/RECORD
