Metadata-Version: 2.1
Name: seolTest
Version: 0.0.0.2
Summary: My First Test Package
Home-page: https://blog.naver.com/rlatjf608
Author: Seol Kim
Author-email: rlatjf60854@gmail.com
License: MIT
Platform: UNKNOWN
Requires-Python: >=3
